LICENSE
MANIFEST.in
README.md
setup.py
tests/__init__.py
tests/http_response_catcher.py
tests/test_helper.py
tests/controllers/__init__.py
tests/controllers/controller_test_base.py
tests/controllers/test_simple_calculator_controller.py
testwithnewimplemenation/__init__.py
testwithnewimplemenation/api_helper.py
testwithnewimplemenation/configuration.py
testwithnewimplemenation/decorators.py
testwithnewimplemenation/testwithnewimplemenation_client.py
testwithnewimplemenation.egg-info/PKG-INFO
testwithnewimplemenation.egg-info/SOURCES.txt
testwithnewimplemenation.egg-info/dependency_links.txt
testwithnewimplemenation.egg-info/requires.txt
testwithnewimplemenation.egg-info/top_level.txt
testwithnewimplemenation/controllers/__init__.py
testwithnewimplemenation/controllers/base_controller.py
testwithnewimplemenation/controllers/simple_calculator_controller.py
testwithnewimplemenation/exceptions/__init__.py
testwithnewimplemenation/exceptions/api_exception.py
testwithnewimplemenation/http/__init__.py
testwithnewimplemenation/http/http_call_back.py
testwithnewimplemenation/http/http_client.py
testwithnewimplemenation/http/http_context.py
testwithnewimplemenation/http/http_method_enum.py
testwithnewimplemenation/http/http_request.py
testwithnewimplemenation/http/http_response.py
testwithnewimplemenation/http/requests_client.py
testwithnewimplemenation/models/__init__.py
testwithnewimplemenation/models/operation_type_enum.py